{
  "date": "2026-05-13",
  "logged": "2026-05-13T18:00:48.154996",
  "config_snapshot": {
    "environment": "live",
    "min_calibrated_score": 65,
    "supported_bet_types": [
      "ml"
    ],
    "max_stake_per_pick_dollars": 5,
    "max_daily_exposure_dollars": 20,
    "kelly_fraction": 0.25,
    "bankroll_dollars": 500,
    "skip_if_yes_ask_above_cents": 80
  },
  "orders": [
    {
      "pick": {
        "sport": "NHL",
        "betType": "ml",
        "home": "Colorado Avalanche",
        "away": "Minnesota Wild",
        "atsPick": "home",
        "spread": null,
        "total": null,
        "pickedTeam": "Colorado Avalanche",
        "pickLabel": "Colorado Avalanche ML (-230)",
        "score100": 80,
        "rawScore100": 66,
        "odds": -230,
        "tier": "elite",
        "factors": [
          {
            "t": "pos",
            "l": "\ud83d\udcca Win rate 78% vs implied 67%"
          },
          {
            "t": "pos",
            "l": "\u26a1 Net RTG edge +8.1"
          },
          {
            "t": "pos",
            "l": "\ud83d\udcb0 Good value at -230"
          }
        ],
        "date": "May 13",
        "time": "8:10 PM ET"
      },
      "market_ticker": "KXNHLGAME-26MAY13MINCOL-COL",
      "market_title": "Game 5: Minnesota at Colorado Winner?",
      "yes_side": "YES",
      "yes_ask_cents": 68,
      "yes_bid_cents": 67,
      "last_price_cents": 68,
      "previous_yes_ask_cents": 66,
      "volume_24h": "161784.74",
      "use_price_cents": 68,
      "use_price_source": "yes_ask",
      "model_prob": 0.8,
      "would_place": true,
      "skip_reason": null,
      "stake_dollars": 4.76,
      "contracts": 7,
      "edge_pct": 0.12,
      "kelly_fraction_used": 0.25,
      "outcome": "win",
      "home_score": 4,
      "away_score": 3,
      "payout_dollars": 7.0,
      "pnl_dollars": 2.24,
      "reconcile_status": "graded"
    }
  ],
  "summary": {
    "picks_total": 9,
    "picks_eligible_after_filter": 1,
    "orders_would_place": 1,
    "total_stake_dollars": 4.76,
    "remaining_daily_capacity": 15.24,
    "skipped_by_reason": {}
  },
  "reconcile": {
    "date": "2026-05-13",
    "placed": 1,
    "wins": 1,
    "losses": 0,
    "pushes": 0,
    "ungraded": 0,
    "total_stake_dollars": 4.76,
    "total_payout_dollars": 7.0,
    "total_pnl_dollars": 2.24,
    "roi_pct": 47.06
  }
}