{
  "days": 11,
  "total_orders_placed": 10,
  "wins": 3,
  "losses": 5,
  "total_stake_dollars": 11.0,
  "total_pnl_dollars": -2.5,
  "roi_pct": -22.73,
  "win_pct": 37.5,
  "track": "paper_ou",
  "daily": [
    {
      "date": "2026-05-20",
      "placed": 4,
      "wins": 2,
      "losses": 2,
      "pushes": 0,
      "ungraded": 0,
      "total_stake_dollars": 4.4,
      "total_pnl_dollars": -0.2,
      "roi_pct": -4.55
    },
    {
      "date": "2026-05-23",
      "placed": 1,
      "wins": 0,
      "losses": 1,
      "pushes": 0,
      "ungraded": 0,
      "total_stake_dollars": 1.1,
      "total_pnl_dollars": -1.1,
      "roi_pct": -100.0
    },
    {
      "date": "2026-05-24",
      "placed": 3,
      "wins": 1,
      "losses": 2,
      "pushes": 0,
      "ungraded": 0,
      "total_stake_dollars": 3.3,
      "total_pnl_dollars": -1.2,
      "roi_pct": -36.36
    },
    {
      "date": "2026-05-25",
      "placed": 2,
      "wins": 0,
      "losses": 0,
      "pushes": 0,
      "ungraded": 2,
      "total_stake_dollars": 2.2,
      "total_pnl_dollars": 0,
      "roi_pct": 0.0
    },
    {
      "date": "2026-05-29",
      "placed": 0,
      "wins": 0,
      "losses": 0,
      "pushes": 0,
      "ungraded": 0,
      "total_stake_dollars": 0.0,
      "total_pnl_dollars": 0,
      "roi_pct": 0,
      "alt_total": {
        "placed": 2,
        "wins": 1,
        "losses": 1,
        "ungraded": 0,
        "cost_dollars": 1.45,
        "pnl_dollars": -0.45,
        "roi_pct": -31.03,
        "win_pct": 50.0
      }
    },
    {
      "date": "2026-05-30",
      "placed": 0,
      "wins": 0,
      "losses": 0,
      "pushes": 0,
      "ungraded": 0,
      "total_stake_dollars": 0.0,
      "total_pnl_dollars": 0,
      "roi_pct": 0,
      "alt_total": {
        "placed": 3,
        "wins": 3,
        "losses": 0,
        "ungraded": 0,
        "cost_dollars": 2.05,
        "pnl_dollars": 0.95,
        "roi_pct": 46.34,
        "win_pct": 100.0
      }
    },
    {
      "date": "2026-05-31",
      "placed": 0,
      "wins": 0,
      "losses": 0,
      "pushes": 0,
      "ungraded": 0,
      "total_stake_dollars": 0.0,
      "total_pnl_dollars": 0,
      "roi_pct": 0,
      "alt_total": {
        "placed": 5,
        "wins": 3,
        "losses": 2,
        "ungraded": 0,
        "cost_dollars": 3.72,
        "pnl_dollars": -0.72,
        "roi_pct": -19.35,
        "win_pct": 60.0
      }
    },
    {
      "date": "2026-06-01",
      "placed": 0,
      "wins": 0,
      "losses": 0,
      "pushes": 0,
      "ungraded": 0,
      "total_stake_dollars": 0.0,
      "total_pnl_dollars": 0,
      "roi_pct": 0,
      "alt_total": {
        "placed": 1,
        "wins": 1,
        "losses": 0,
        "ungraded": 0,
        "cost_dollars": 0.69,
        "pnl_dollars": 0.31,
        "roi_pct": 44.93,
        "win_pct": 100.0
      }
    },
    {
      "date": "2026-06-02",
      "placed": 0,
      "wins": 0,
      "losses": 0,
      "pushes": 0,
      "ungraded": 0,
      "total_stake_dollars": 0.0,
      "total_pnl_dollars": 0,
      "roi_pct": 0,
      "alt_total": {
        "placed": 5,
        "wins": 4,
        "losses": 1,
        "ungraded": 0,
        "cost_dollars": 3.12,
        "pnl_dollars": 0.88,
        "roi_pct": 28.21,
        "win_pct": 80.0
      }
    },
    {
      "date": "2026-06-03",
      "placed": 0,
      "wins": 0,
      "losses": 0,
      "pushes": 0,
      "ungraded": 0,
      "total_stake_dollars": 0.0,
      "total_pnl_dollars": 0,
      "roi_pct": 0,
      "alt_total": {
        "placed": 1,
        "wins": 1,
        "losses": 0,
        "ungraded": 0,
        "cost_dollars": 0.65,
        "pnl_dollars": 0.35,
        "roi_pct": 53.85,
        "win_pct": 100.0
      }
    },
    {
      "date": "2026-06-04",
      "placed": 0,
      "wins": 0,
      "losses": 0,
      "pushes": 0,
      "ungraded": 0,
      "total_stake_dollars": 0.0,
      "total_pnl_dollars": 0,
      "roi_pct": 0,
      "alt_total": {
        "placed": 5,
        "wins": 3,
        "losses": 2,
        "ungraded": 0,
        "cost_dollars": 3.75,
        "pnl_dollars": -0.75,
        "roi_pct": -20.0,
        "win_pct": 60.0
      }
    }
  ]
}